{
  "success": true,
  "data": {
    "followers": [
      {
        "id": "124",
        "firstName": "Jane",
        "lastName": "Smith",
        "avatarUrl": "https://api.dicebear.com/7.x/avataaars/svg?seed=Jane",
        "mutualCount": 12
      },
      {
        "id": "125",
        "firstName": "Alex",
        "lastName": "Johnson",
        "avatarUrl": "https://api.dicebear.com/7.x/avataaars/svg?seed=Alex",
        "mutualCount": 8
      },
      {
        "id": "126",
        "firstName": "Sarah",
        "lastName": "Williams",
        "avatarUrl": "https://api.dicebear.com/7.x/avataaars/svg?seed=Sarah",
        "mutualCount": 15
      }
    ]
  },
  "meta": {
    "page": 1,
    "limit": 20,
    "total": 3,
    "hasMore": false
  },
  "timestamp": "2024-12-07T10:30:00Z"
}